Workbook

Sheet Dashboard
A1: INVESTING × HOME OWNERSHIP CALCULATOR
A2: Only Change Values in the Blue Cells. Red Coloured cells are showing values after calculations. The calculation engine lives on 2 hidden sheets named "Calc1" and "Calc2".
A4: INCOME & TIMELINE
B5: Partner 1 income (per year) | C5: Partner 2 income (per year) | D5: Household after-tax (per year) | E5: Household after-tax (per month) | F5: Starting age (today) | G5: Model start — year | H5: Model start — month | I5: Financial plan starts at age (ramp target) | J5: Show final balance at age
B6: 120000 | C6: 80000 | D6: =B6-IF(B6<=18200,0,IF(B6<=45000,(B6-18200)*0.16,IF(B6<=135000,4288+(B6-45000)*0.3,IF(B6<=190000,31288+(B6-135000)*0.37,51638+(B6-190000)*0.45))))+C6-IF(C6<=18200,0,IF(C6<=45000,(C6-18200)*0.16,IF(C6<=135000,4288+(C6-45000)*0.3,IF(C6<=190000,31288+(C6-135000)*0.37,51638+(C6-190000)*0.45)))) -> 158424 | E6: =D6/12 -> 13202 | F6: =18+20/365 -> 18.054795 | G6: 2025 | H6: 7 | I6: 25 | J6: 60
A8: RATES & CONTRIBUTIONS
B9: Investment return (EAR) | C9: Post-retirement return (EAR) | D9: Mortgage rate (p.a.) | E9: Inflation / CPI (p.a.) | F9: Splurge (% of after-tax) | G9: First-month lump investment | H9: Minimum monthly contribution | I9: Saving bucket (minimum cash saved per month) | J9: Living expenses (per month)
B10: 0.1 | C10: 0.1 | D10: 0.06 | E10: 0.025 | F10: 0.1 | G10: 100000 | H10: 500 | I10: 500 | J10: =H14 -> 4500
A12: MONTHLY EXPENSES
B13: Insurance | C13: Groceries | D13: Eating out | E13: Bills | F13: Car | G13: Miscallenous | H13: Total expenses / month
B14: 800 | C14: 700 | D14: 1000 | E14: 550 | F14: 700 | G14: 750 | H14: =SUM(B14:G14) -> 4500
A16: CGT — 2026-27 REFORM MODEL
B17: Marginal rate (incl. levies) | C17: Post-reform minimum rate | D17: Reform cutoff — year | E17: Reform cutoff — month
B18: 0.47 | C18: 0.3 | D18: 2027 | E18: 7
A20: STRATEGY INPUTS
B21: STRATEGY | C21: Rent (per month) | D21: Buy house at age | E21: Mortgage length (years) | F21: Retire — drawdowns start at age | G21: House price | H21: Deposit % | I21: Deposit funded from portfolio? (1 = yes, 0 = no)
B22: STRATEGY 1 · Rent first, buy later | C22: 6000 | D22: 35 | E22: 20 | F22: 50 | G22: 300000 | H22: 1 | I22: 1
B23: STRATEGY 2 · Buy at 25, no rent | C23: 0 | D23: 25 | E23: 30 | F23: 50 | G23: 894067.57 | H23: 0.05 | I23: 1
A25: DERIVED
B26: STRATEGY | C26: Years renting (plan → purchase) | D26: Deposit ($) | E26: Loan amount | F26: Monthly repayment | G26: Mortgage paid off at age | H26: Investing / month — renting phase | I26: Investing / month — mortgage phase | J26: Investing / month — after payoff | K26: Target monthly investing (hit at plan age) | L26: Contribution ramp (growth per month)
B27: STRATEGY 1 · Rent first, buy later | C27: =MAX(0,D22-$I$6) -> 10 | D27: =Calc1!$N$2 -> 300000 | E27: =Calc1!$O$2 -> 0 | F27: =Calc1!$P$2 -> 0 | G27: =D22+E22 -> 55 | H27: =Calc1!$K$2 -> 881.8 | I27: =Calc1!$L$2 -> 6881.8 | J27: =Calc1!$M$2 -> 6881.8 | K27: =Calc1!$J$2 -> 881.8 | L27: =IF(Calc1!$J$2<=$H$10,0,POWER(Calc1!$J$2/$H$10,1/Calc1!$D$2)-1) -> 0.0068590448
B28: STRATEGY 2 · Buy at 25, no rent | C28: =MAX(0,D23-$I$6) -> 0 | D28: =Calc2!$N$2 -> 44703.378 | E28: =Calc2!$O$2 -> 849364.19 | F28: =Calc2!$P$2 -> 5092.3675 | G28: =D23+E23 -> 55 | H28: =Calc2!$K$2 -> 6881.8 | I28: =Calc2!$L$2 -> 1789.4325 | J28: =Calc2!$M$2 -> 6881.8 | K28: =Calc2!$J$2 -> 1789.4325 | L28: =IF(Calc2!$J$2<=$H$10,0,POWER(Calc2!$J$2/$H$10,1/Calc2!$D$2)-1) -> 0.015480599
A30: RESULTS
B31: STRATEGY | C31: Portfolio just before buying | D31: Sold to fund deposit (incl. CGT) | E31: CGT paid on that sale | F31: Portfolio at retirement | G31: Monthly need at retirement (after-tax) | H31: Monthly drawdown at retirement (pre-tax) | I31: Balance at final age | J31: Lowest balance after retiring | K31: Money runs out before 75?
B32: STRATEGY 1 · Rent first, buy later | C32: =INDEX(Calc1!$K$5:$K$688,MIN(Calc1!$E$2,684)) -> 875524.48 | D32: =Calc1!$W$2 -> 414318.53 | E32: =IF(I22=1,Calc1!$W$2-Calc1!$N$2,0) -> 114318.53 | F32: =INDEX(Calc1!$K$5:$K$688,MIN(Calc1!$F$2,683)+1) -> 4719855.5 | G32: =INDEX(Calc1!$F$5:$F$688,MIN(Calc1!$F$2,683)+1) -> 6320.2 | H32: =INDEX(Calc1!$G$5:$G$688,MIN(Calc1!$F$2,683)+1) -> 7932.1905 | I32: =INDEX(Calc1!$K$5:$K$688,MIN(Calc1!$G$2,683)+1) -> 10437418 | J32: =MIN(Calc1!$L$5:$L$688) -> 4719855.5 | K32: =IF(MIN(Calc1!$K$5:$K$688)<0,"YES ⚠","No") -> No
B33: STRATEGY 2 · Buy at 25, no rent | C33: =INDEX(Calc2!$K$5:$K$688,MIN(Calc2!$E$2,684)) -> 302847.37 | D33: =Calc2!$W$2 -> 51751.156 | E33: =IF(I23=1,Calc2!$W$2-Calc2!$N$2,0) -> 7047.7779 | F33: =INDEX(Calc2!$K$5:$K$688,MIN(Calc2!$F$2,683)+1) -> 4968765.4 | G33: =INDEX(Calc2!$F$5:$F$688,MIN(Calc2!$F$2,683)+1) -> 11412.567 | H33: =INDEX(Calc2!$G$5:$G$688,MIN(Calc2!$F$2,683)+1) -> 15646.668 | I33: =INDEX(Calc2!$K$5:$K$688,MIN(Calc2!$G$2,683)+1) -> 10121889 | J33: =MIN(Calc2!$L$5:$L$688) -> 4968765.4 | K33: =IF(MIN(Calc2!$K$5:$K$688)<0,"YES ⚠","No") -> No
B35: Strategy 2 minus Strategy 1 — balance at final age | I35: =I33-I32 -> -315528.92
A37: PORTFOLIO OVER TIME
A58: NOTES & ASSUMPTIONS
B59: • Monthly investing = after-tax income − housing − saving − expenses − splurge. Housing switches automatically: $0 before the plan age → rent → mortgage repayment → $0 after payoff, so money freed up by the mortgage ending is invested.
B60: • Contribution ramp: starts at the minimum contribution and grows geometrically so it reaches the target monthly investing amount exactly at the plan-start age (cell I6).
B61: • Retirement drawdown = (saving + expenses + splurge, indexed at CPI from retirement) + housing still owed (rent indexed; mortgage repayments fixed until payoff).
B62: • After tax figures are for 2026/2027 income tax. Note this may change in the future and may change the after tax figure.
B63: • Treat Monthly expenses columns as guides, total monthly expenses can also be entered in cell H14 directly.
B64: • Importantly, for specific retirement balances, the Solver function (Data - > Solver) can be used to determine adequte house prices (Cells G22 and G23)

Sheet Calc1
A1: gm /mo | B1: post /mo | C1: cpi /mo | D1: M ramp | E1: S buy | F1: S retire | G1: S final | H1: n mort | I1: afterTax/mo | J1: target inv | K1: inv rent | L1: inv mort | M1: inv paid | N1: deposit | O1: loan | P1: repayment | Q1: start abs | R1: cutoff abs | S1: sale abs | T1: tot value | U1: tot tax | V1: gross factor | W1: gross w/d | X1: needs base
A2: =(1+Dashboard!$B$10)^(1/12)-1 -> 0.0079741404 | B2: =(1+Dashboard!$C$10)^(1/12)-1 -> 0.0079741404 | C2: =(1+Dashboard!$E$10)^(1/12)-1 -> 0.0020598363 | D2: =MAX(1,ROUND((Dashboard!$I$6-Dashboard!$F$6)*12,0)) -> 83 | E2: =MAX(1,ROUND((Dashboard!$D$22-Dashboard!$F$6)*12,0)) -> 203 | F2: =MAX(1,ROUND((Dashboard!$F$22-Dashboard!$F$6)*12,0)) -> 383 | G2: =ROUND((Dashboard!$J$6-Dashboard!$F$6)*12,0) -> 503 | H2: =Dashboard!$E$22*12 -> 240 | I2: =Dashboard!$E$6 -> 13202 | J2: =$I$2-IF(Dashboard!$D$22<=Dashboard!$I$6,$P$2,Dashboard!$C$22)-Dashboard!$I$10-Dashboard!$J$10-Dashboard!$F$10*$I$2 -> 881.8 | K2: =$I$2-Dashboard!$C$22-Dashboard!$I$10-Dashboard!$J$10-Dashboard!$F$10*$I$2 -> 881.8 | L2: =$I$2-$P$2-Dashboard!$I$10-Dashboard!$J$10-Dashboard!$F$10*$I$2 -> 6881.8 | M2: =$I$2-Dashboard!$I$10-Dashboard!$J$10-Dashboard!$F$10*$I$2 -> 6881.8 | N2: =Dashboard!$G$22*Dashboard!$H$22 -> 300000 | O2: =Dashboard!$G$22-$N$2 -> 0 | P2: =IF(OR($O$2<=0,$H$2<=0),0,-PMT(Dashboard!$D$10/12,$H$2,$O$2)) -> 0 | Q2: =Dashboard!$G$6*12+Dashboard!$H$6-1 -> 24306 | R2: =Dashboard!$D$18*12+Dashboard!$E$18-1 -> 24330 | S2: =$Q$2+$E$2 -> 24509 | T2: =SUM($M$5:$M$688) -> 875524.48 | U2: =SUM($N$5:$N$688) -> 241574.21 | V2: =IF($T$2-$U$2>0,$T$2/($T$2-$U$2),1) -> 1.3810618 | W2: =$N$2*$V$2*Dashboard!$I$22 -> 414318.53 | X2: =Dashboard!$I$10+Dashboard!$J$10+Dashboard!$F$10*$I$2 -> 6320.2
A4: Period | B4: Age | C4: Age label | D4: Housing | E4: Contribution | F4: Need (after-tax) | G4: Drawdown (pre-tax) | H4: Purchase w/d | I4: Net flow | J4: Rate /mo | K4: Portfolio | L4: Post-ret balance | M4: Parcel value @ sale | N4: Parcel CGT
A5: 0 | B5: =Dashboard!$F$6 -> 18.054795 | C5: =INT(B5)&" y "&ROUND((B5-INT(B5))*12,2)&" m" -> 18 y 0.66 m | D5: =IF(A5>=$E$2,IF(A5<$E$2+$H$2,$P$2,0),IF(B5<Dashboard!$I$6,0,IF(A5>=$F$2,Dashboard!$C$22*POWER(1+$C$2,A5-$F$2),Dashboard!$C$22))) -> 0 | E5: =IF(A5>=$F$2,0,IF(A5=0,Dashboard!$G$10,IF(B5<Dashboard!$I$6,IF($J$2<=Dashboard!$H$10,Dashboard!$H$10,MAX(Dashboard!$H$10,MIN($J$2,Dashboard!$H$10*POWER($J$2/Dashboard!$H$10,A5/$D$2)))),$I$2-D5-Dashboard!$I$10-Dashboard!$J$10-Dashboard!$F$10*$I$2))) -> 100000 | F5: =IF(A5>=$F$2,$X$2*POWER(1+$C$2,A5-$F$2)+D5,0) -> 0 | G5: =IF(F5<=0,0,IF(F5*12<=18200,F5,IF(F5*12<=40712,(18200+(F5*12-18200)/0.84)/12,IF(F5*12<=103712,(45000+(F5*12-40712)/0.7)/12,IF(F5*12<=138362,(135000+(F5*12-103712)/0.63)/12,(190000+(F5*12-138362)/0.55)/12))))) -> 0 | H5: =IF(A5=$E$2,$W$2,0) -> 0 | I5: =E5-G5-H5 -> 100000 | J5: =IF(A5>=$F$2,$B$2,$A$2) -> 0.0079741404 | K5: =I5*(1+J5) -> 100797.41 | L5: =IF(A5>=$F$2,K5,"") | M5: =IF(AND(A5<$E$2,E5>0),E5*POWER(1+$A$2,$E$2-A5),0) -> 501448.41 | N5: =IF(M5<=0,0,IF($E$2-A5<12,(M5-E5)*Dashboard!$B$18,IF($Q$2+A5>=$R$2,MAX(0,M5-E5*POWER(1+$C$2,$E$2-A5))*MAX(Dashboard!$C$18,Dashboard!$B$18),IF($S$2<$R$2,(M5-E5)*0.5*Dashboard!$B$18,(E5*POWER(1+$A$2,$R$2-($Q$2+A5))-E5)*0.5*Dashboard!$B$18+MAX(0,M5-E5*POWER(1+$A$2,$R$2-($Q$2+A5))*POWER(1+$C$2,$S$2-$R$2))*MAX(Dashboard!$C$18,Dashboard!$B$18))))) -> 158420.34
A6: =A5+1 -> 1 | B6: =B5+1/12 -> 18.138128 | C6: =INT(B6)&" y "&ROUND((B6-INT(B6))*12,2)&" m" -> 18 y 1.66 m | D6: =IF(A6>=$E$2,IF(A6<$E$2+$H$2,$P$2,0),IF(B6<Dashboard!$I$6,0,IF(A6>=$F$2,Dashboard!$C$22*POWER(1+$C$2,A6-$F$2),Dashboard!$C$22))) -> 0 | E6: =IF(A6>=$F$2,0,IF(A6=0,Dashboard!$G$10,IF(B6<Dashboard!$I$6,IF($J$2<=Dashboard!$H$10,Dashboard!$H$10,MAX(Dashboard!$H$10,MIN($J$2,Dashboard!$H$10*POWER($J$2/Dashboard!$H$10,A6/$D$2)))),$I$2-D6-Dashboard!$I$10-Dashboard!$J$10-Dashboard!$F$10*$I$2))) -> 503.42952 | F6: =IF(A6>=$F$2,$X$2*POWER(1+$C$2,A6-$F$2)+D6,0) -> 0 | G6: =IF(F6<=0,0,IF(F6*12<=18200,F6,IF(F6*12<=40712,(18200+(F6*12-18200)/0.84)/12,IF(F6*12<=103712,(45000+(F6*12-40712)/0.7)/12,IF(F6*12<=138362,(135000+(F6*12-103712)/0.63)/12,(190000+(F6*12-138362)/0.55)/12))))) -> 0 | H6: =IF(A6=$E$2,$W$2,0) -> 0 | I6: =E6-G6-H6 -> 503.42952 | J6: =IF(A6>=$F$2,$B$2,$A$2) -> 0.0079741404 | K6: =(K5+I6)*(1+J6) -> 102108.63 | L6: =IF(A6>=$F$2,K6,"") | M6: =IF(AND(A6<$E$2,E6>0),E6*POWER(1+$A$2,$E$2-A6),0) -> 2504.4683 | N6: =IF(M6<=0,0,IF($E$2-A6<12,(M6-E6)*Dashboard!$B$18,IF($Q$2+A6>=$R$2,MAX(0,M6-E6*POWER(1+$C$2,$E$2-A6))*MAX(Dashboard!$C$18,Dashboard!$B$18),IF($S$2<$R$2,(M6-E6)*0.5*Dashboard!$B$18,(E6*POWER(1+$A$2,$R$2-($Q$2+A6))-E6)*0.5*Dashboard!$B$18+MAX(0,M6-E6*POWER(1+$A$2,$R$2-($Q$2+A6))*POWER(1+$C$2,$S$2-$R$2))*MAX(Dashboard!$C$18,Dashboard!$B$18))))) -> 790.28952
A7: =A6+1 -> 2 | B7: =B6+1/12 -> 18.221461 | C7: =INT(B7)&" y "&ROUND((B7-INT(B7))*12,2)&" m" -> 18 y 2.66 m | D7: =IF(A7>=$E$2,IF(A7<$E$2+$H$2,$P$2,0),IF(B7<Dashboard!$I$6,0,IF(A7>=$F$2,Dashboard!$C$22*POWER(1+$C$2,A7-$F$2),Dashboard!$C$22))) -> 0 | E7: =IF(A7>=$F$2,0,IF(A7=0,Dashboard!$G$10,IF(B7<Dashboard!$I$6,IF($J$2<=Dashboard!$H$10,Dashboard!$H$10,MAX(Dashboard!$H$10,MIN($J$2,Dashboard!$H$10*POWER($J$2/Dashboard!$H$10,A7/$D$2)))),$I$2-D7-Dashboard!$I$10-Dashboard!$J$10-Dashboard!$F$10*$I$2))) -> 506.88257 | F7: =IF(A7>=$F$2,$X$2*POWER(1+$C$2,A7-$F$2)+D7,0) -> 0 | G7: =IF(F7<=0,0,IF(F7*12<=18200,F7,IF(F7*12<=40712,(18200+(F7*12-18200)/0.84)/12,IF(F7*12<=103712,(45000+(F7*12-40712)/0.7)/12,IF(F7*12<=138362,(135000+(F7*12-103712)/0.63)/12,(190000+(F7*12-138362)/0.55)/12))))) -> 0 | H7: =IF(A7=$E$2,$W$2,0) -> 0 | I7: =E7-G7-H7 -> 506.88257 | J7: =IF(A7>=$F$2,$B$2,$A$2) -> 0.0079741404 | K7: =(K6+I7)*(1+J7) -> 103433.78 | L7: =IF(A7>=$F$2,K7,"") | M7: =IF(AND(A7<$E$2,E7>0),E7*POWER(1+$A$2,$E$2-A7),0) -> 2501.6977 | N7: =IF(M7<=0,0,IF($E$2-A7<12,(M7-E7)*Dashboard!$B$18,IF($Q$2+A7>=$R$2,MAX(0,M7-E7*POWER(1+$C$2,$E$2-A7))*MAX(Dashboard!$C$18,Dashboard!$B$18),IF($S$2<$R$2,(M7-E7)*0.5*Dashboard!$B$18,(E7*POWER(1+$A$2,$R$2-($Q$2+A7))-E7)*0.5*Dashboard!$B$18+MAX(0,M7-E7*POWER(1+$A$2,$R$2-($Q$2+A7))*POWER(1+$C$2,$S$2-$R$2))*MAX(Dashboard!$C$18,Dashboard!$B$18))))) -> 788.47289
A8: =A7+1 -> 3 | B8: =B7+1/12 -> 18.304795 | C8: =INT(B8)&" y "&ROUND((B8-INT(B8))*12,2)&" m" -> 18 y 3.66 m | D8: =IF(A8>=$E$2,IF(A8<$E$2+$H$2,$P$2,0),IF(B8<Dashboard!$I$6,0,IF(A8>=$F$2,Dashboard!$C$22*POWER(1+$C$2,A8-$F$2),Dashboard!$C$22))) -> 0 | E8: =IF(A8>=$F$2,0,IF(A8=0,Dashboard!$G$10,IF(B8<Dashboard!$I$6,IF($J$2<=Dashboard!$H$10,Dashboard!$H$10,MAX(Dashboard!$H$10,MIN($J$2,Dashboard!$H$10*POWER($J$2/Dashboard!$H$10,A8/$D$2)))),$I$2-D8-Dashboard!$I$10-Dashboard!$J$10-Dashboard!$F$10*$I$2))) -> 510.3593 | F8: =IF(A8>=$F$2,$X$2*POWER(1+$C$2,A8-$F$2)+D8,0) -> 0 | G8: =IF(F8<=0,0,IF(F8*12<=18200,F8,IF(F8*12<=40712,(18200+(F8*12-18200)/0.84)/12,IF(F8*12<=103712,(45000+(F8*12-40712)/0.7)/12,IF(F8*12<=138362,(135000+(F8*12-103712)/0.63)/12,(190000+(F8*12-138362)/0.55)/12))))) -> 0 | H8: =IF(A8=$E$2,$W$2,0) -> 0 | I8: =E8-G8-H8 -> 510.3593 | J8: =IF(A8>=$F$2,$B$2,$A$2) -> 0.0079741404 | K8: =(K7+I8)*(1+J8) -> 104773.01 | L8: =IF(A8>=$F$2,K8,"") | M8: =IF(AND(A8<$E$2,E8>0),E8*POWER(1+$A$2,$E$2-A8),0) -> 2498.9302 | N8: =IF(M8<=0,0,IF($E$2-A8<12,(M8-E8)*Dashboard!$B$18,IF($Q$2+A8>=$R$2,MAX(0,M8-E8*POWER(1+$C$2,$E$2-A8))*MAX(Dashboard!$C$18,Dashboard!$B$18),IF($S$2<$R$2,(M8-E8)*0.5*Dashboard!$B$18,(E8*POWER(1+$A$2,$R$2-($Q$2+A8))-E8)*0.5*Dashboard!$B$18+MAX(0,M8-E8*POWER(1+$A$2,$R$2-($Q$2+A8))*POWER(1+$C$2,$S$2-$R$2))*MAX(Dashboard!$C$18,Dashboard!$B$18))))) -> 786.65182
A9: =A8+1 -> 4 | B9: =B8+1/12 -> 18.388128 | C9: =INT(B9)&" y "&ROUND((B9-INT(B9))*12,2)&" m" -> 18 y 4.66 m | D9: =IF(A9>=$E$2,IF(A9<$E$2+$H$2,$P$2,0),IF(B9<Dashboard!$I$6,0,IF(A9>=$F$2,Dashboard!$C$22*POWER(1+$C$2,A9-$F$2),Dashboard!$C$22))) -> 0 | E9: =IF(A9>=$F$2,0,IF(A9=0,Dashboard!$G$10,IF(B9<Dashboard!$I$6,IF($J$2<=Dashboard!$H$10,Dashboard!$H$10,MAX(Dashboard!$H$10,MIN($J$2,Dashboard!$H$10*POWER($J$2/Dashboard!$H$10,A9/$D$2)))),$I$2-D9-Dashboard!$I$10-Dashboard!$J$10-Dashboard!$F$10*$I$2))) -> 513.85988 | F9: =IF(A9>=$F$2,$X$2*POWER(1+$C$2,A9-$F$2)+D9,0) -> 0 | G9: =IF(F9<=0,0,IF(F9*12<=18200,F9,IF(F9*12<=40712,(18200+(F9*12-18200)/0.84)/12,IF(F9*12<=103712,(45000+(F9*12-40712)/0.7)/12,IF(F9*12<=138362,(135000+(F9*12-103712)/0.63)/12,(190000+(F9*12-138362)/0.55)/12))))) -> 0 | H9: =IF(A9=$E$2,$W$2,0) -> 0 | I9: =E9-G9-H9 -> 513.85988 | J9: =IF(A9>=$F$2,$B$2,$A$2) -> 0.0079741404 | K9: =(K8+I9)*(1+J9) -> 106126.44 | L9: =IF(A9>=$F$2,K9,"") | M9: =IF(AND(A9<$E$2,E9>0),E9*POWER(1+$A$2,$E$2-A9),0) -> 2496.1657 | N9: =IF(M9<=0,0,IF($E$2-A9<12,(M9-E9)*Dashboard!$B$18,IF($Q$2+A9>=$R$2,MAX(0,M9-E9*POWER(1+$C$2,$E$2-A9))*MAX(Dashboard!$C$18,Dashboard!$B$18),IF($S$2<$R$2,(M9-E9)*0.5*Dashboard!$B$18,(E9*POWER(1+$A$2,$R$2-($Q$2+A9))-E9)*0.5*Dashboard!$B$18+MAX(0,M9-E9*POWER(1+$A$2,$R$2-($Q$2+A9))*POWER(1+$C$2,$S$2-$R$2))*MAX(Dashboard!$C$18,Dashboard!$B$18))))) -> 784.82625
A10: =A9+1 -> 5 | B10: =B9+1/12 -> 18.471461 | C10: =INT(B10)&" y "&ROUND((B10-INT(B10))*12,2)&" m" -> 18 y 5.66 m | D10: =IF(A10>=$E$2,IF(A10<$E$2+$H$2,$P$2,0),IF(B10<Dashboard!$I$6,0,IF(A10>=$F$2,Dashboard!$C$22*POWER(1+$C$2,A10-$F$2),Dashboard!$C$22))) -> 0 | E10: =IF(A10>=$F$2,0,IF(A10=0,Dashboard!$G$10,IF(B10<Dashboard!$I$6,IF($J$2<=Dashboard!$H$10,Dashboard!$H$10,MAX(Dashboard!$H$10,MIN($J$2,Dashboard!$H$10*POWER($J$2/Dashboard!$H$10,A10/$D$2)))),$I$2-D10-Dashboard!$I$10-Dashboard!$J$10-Dashboard!$F$10*$I$2))) -> 517.38446 | F10: =IF(A10>=$F$2,$X$2*POWER(1+$C$2,A10-$F$2)+D10,0) -> 0 | G10: =IF(F10<=0,0,IF(F10*12<=18200,F10,IF(F10*12<=40712,(18200+(F10*12-18200)/0.84)/12,IF(F10*12<=103712,(45000+(F10*12-40712)/0.7)/12,IF(F10*12<=138362,(135000+(F10*12-103712)/0.63)/12,(190000+(F10*12-138362)/0.55)/12))))) -> 0 | H10: =IF(A10=$E$2,$W$2,0) -> 0 | I10: =E10-G10-H10 -> 517.38446 | J10: =IF(A10>=$F$2,$B$2,$A$2) -> 0.0079741404 | K10: =(K9+I10)*(1+J10) -> 107494.22 | L10: =IF(A10>=$F$2,K10,"") | M10: =IF(AND(A10<$E$2,E10>0),E10*POWER(1+$A$2,$E$2-A10),0) -> 2493.4042 | N10: =IF(M10<=0,0,IF($E$2-A10<12,(M10-E10)*Dashboard!$B$18,IF($Q$2+A10>=$R$2,MAX(0,M10-E10*POWER(1+$C$2,$E$2-A10))*MAX(Dashboard!$C$18,Dashboard!$B$18),IF($S$2<$R$2,(M10-E10)*0.5*Dashboard!$B$18,(E10*POWER(1+$A$2,$R$2-($Q$2+A10))-E10)*0.5*Dashboard!$B$18+MAX(0,M10-E10*POWER(1+$A$2,$R$2-($Q$2+A10))*POWER(1+$C$2,$S$2-$R$2))*MAX(Dashboard!$C$18,Dashboard!$B$18))))) -> 782.99615
A11: =A10+1 -> 6 | B11: =B10+1/12 -> 18.554795 | C11: =INT(B11)&" y "&ROUND((B11-INT(B11))*12,2)&" m" -> 18 y 6.66 m | D11: =IF(A11>=$E$2,IF(A11<$E$2+$H$2,$P$2,0),IF(B11<Dashboard!$I$6,0,IF(A11>=$F$2,Dashboard!$C$22*POWER(1+$C$2,A11-$F$2),Dashboard!$C$22))) -> 0 | E11: =IF(A11>=$F$2,0,IF(A11=0,Dashboard!$G$10,IF(B11<Dashboard!$I$6,IF($J$2<=Dashboard!$H$10,Dashboard!$H$10,MAX(Dashboard!$H$10,MIN($J$2,Dashboard!$H$10*POWER($J$2/Dashboard!$H$10,A11/$D$2)))),$I$2-D11-Dashboard!$I$10-Dashboard!$J$10-Dashboard!$F$10*$I$2))) -> 520.93323 | F11: =IF(A11>=$F$2,$X$2*POWER(1+$C$2,A11-$F$2)+D11,0) -> 0 | G11: =IF(F11<=0,0,IF(F11*12<=18200,F11,IF(F11*12<=40712,(18200+(F11*12-18200)/0.84)/12,IF(F11*12<=103712,(45000+(F11*12-40712)/0.7)/12,IF(F11*12<=138362,(135000+(F11*12-103712)/0.63)/12,(190000+(F11*12-138362)/0.55)/12))))) -> 0 | H11: =IF(A11=$E$2,$W$2,0) -> 0 | I11: =E11-G11-H11 -> 520.93323 | J11: =IF(A11>=$F$2,$B$2,$A$2) -> 0.0079741404 | K11: =(K10+I11)*(1+J11) -> 108876.48 | L11: =IF(A11>=$F$2,K11,"") | M11: =IF(AND(A11<$E$2,E11>0),E11*POWER(1+$A$2,$E$2-A11),0) -> 2490.6458 | N11: =IF(M11<=0,0,IF($E$2-A11<12,(M11-E11)*Dashboard!$B$18,IF($Q$2+A11>=$R$2,MAX(0,M11-E11*POWER(1+$C$2,$E$2-A11))*MAX(Dashboard!$C$18,Dashboard!$B$18),IF($S$2<$R$2,(M11-E11)*0.5*Dashboard!$B$18,(E11*POWER(1+$A$2,$R$2-($Q$2+A11))-E11)*0.5*Dashboard!$B$18+MAX(0,M11-E11*POWER(1+$A$2,$R$2-($Q$2+A11))*POWER(1+$C$2,$S$2-$R$2))*MAX(Dashboard!$C$18,Dashboard!$B$18))))) -> 781.16147
A12: =A11+1 -> 7 | B12: =B11+1/12 -> 18.638128 | C12: =INT(B12)&" y "&ROUND((B12-INT(B12))*12,2)&" m" -> 18 y 7.66 m | D12: =IF(A12>=$E$2,IF(A12<$E$2+$H$2,$P$2,0),IF(B12<Dashboard!$I$6,0,IF(A12>=$F$2,Dashboard!$C$22*POWER(1+$C$2,A12-$F$2),Dashboard!$C$22))) -> 0 | E12: =IF(A12>=$F$2,0,IF(A12=0,Dashboard!$G$10,IF(B12<Dashboard!$I$6,IF($J$2<=Dashboard!$H$10,Dashboard!$H$10,MAX(Dashboard!$H$10,MIN($J$2,Dashboard!$H$10*POWER($J$2/Dashboard!$H$10,A12/$D$2)))),$I$2-D12-Dashboard!$I$10-Dashboard!$J$10-Dashboard!$F$10*$I$2))) -> 524.50633 | F12: =IF(A12>=$F$2,$X$2*POWER(1+$C$2,A12-$F$2)+D12,0) -> 0 | G12: =IF(F12<=0,0,IF(F12*12<=18200,F12,IF(F12*12<=40712,(18200+(F12*12-18200)/0.84)/12,IF(F12*12<=103712,(45000+(F12*12-40712)/0.7)/12,IF(F12*12<=138362,(135000+(F12*12-103712)/0.63)/12,(190000+(F12*12-138362)/0.55)/12))))) -> 0 | H12: =IF(A12=$E$2,$W$2,0) -> 0 | I12: =E12-G12-H12 -> 524.50633 | J12: =IF(A12>=$F$2,$B$2,$A$2) -> 0.0079741404 | K12: =(K11+I12)*(1+J12) -> 110273.36 | L12: =IF(A12>=$F$2,K12,"") | M12: =IF(AND(A12<$E$2,E12>0),E12*POWER(1+$A$2,$E$2-A12),0) -> 2487.8905 | N12: =IF(M12<=0,0,IF($E$2-A12<12,(M12-E12)*Dashboard!$B$18,IF($Q$2+A12>=$R$2,MAX(0,M12-E12*POWER(1+$C$2,$E$2-A12))*MAX(Dashboard!$C$18,Dashboard!$B$18),IF($S$2<$R$2,(M12-E12)*0.5*Dashboard!$B$18,(E12*POWER(1+$A$2,$R$2-($Q$2+A12))-E12)*0.5*Dashboard!$B$18+MAX(0,M12-E12*POWER(1+$A$2,$R$2-($Q$2+A12))*POWER(1+$C$2,$S$2-$R$2))*MAX(Dashboard!$C$18,Dashboard!$B$18))))) -> 779.32219
A13: =A12+1 -> 8 | B13: =B12+1/12 -> 18.721461 | C13: =INT(B13)&" y "&ROUND((B13-INT(B13))*12,2)&" m" -> 18 y 8.66 m | D13: =IF(A13>=$E$2,IF(A13<$E$2+$H$2,$P$2,0),IF(B13<Dashboard!$I$6,0,IF(A13>=$F$2,Dashboard!$C$22*POWER(1+$C$2,A13-$F$2),Dashboard!$C$22))) -> 0 | E13: =IF(A13>=$F$2,0,IF(A13=0,Dashboard!$G$10,IF(B13<Dashboard!$I$6,IF($J$2<=Dashboard!$H$10,Dashboard!$H$10,MAX(Dashboard!$H$10,MIN($J$2,Dashboard!$H$10*POWER($J$2/Dashboard!$H$10,A13/$D$2)))),$I$2-D13-Dashboard!$I$10-Dashboard!$J$10-Dashboard!$F$10*$I$2))) -> 528.10394 | F13: =IF(A13>=$F$2,$X$2*POWER(1+$C$2,A13-$F$2)+D13,0) -> 0 | G13: =IF(F13<=0,0,IF(F13*12<=18200,F13,IF(F13*12<=40712,(18200+(F13*12-18200)/0.84)/12,IF(F13*12<=103712,(45000+(F13*12-40712)/0.7)/12,IF(F13*12<=138362,(135000+(F13*12-103712)/0.63)/12,(190000+(F13*12-138362)/0.55)/12))))) -> 0 | H13: =IF(A13=$E$2,$W$2,0) -> 0 | I13: =E13-G13-H13 -> 528.10394 | J13: =IF(A13>=$F$2,$B$2,$A$2) -> 0.0079741404 | K13: =(K12+I13)*(1+J13) -> 111685.01 | L13: =IF(A13>=$F$2,K13,"") | M13: =IF(AND(A13<$E$2,E13>0),E13*POWER(1+$A$2,$E$2-A13),0) -> 2485.1382 | N13: =IF(M13<=0,0,IF($E$2-A13<12,(M13-E13)*Dashboard!$B$18,IF($Q$2+A13>=$R$2,MAX(0,M13-E13*POWER(1+$C$2,$E$2-A13))*MAX(Dashboard!$C$18,Dashboard!$B$18),IF($S$2<$R$2,(M13-E13)*0.5*Dashboard!$B$18,(E13*POWER(1+$A$2,$R$2-($Q$2+A13))-E13)*0.5*Dashboard!$B$18+MAX(0,M13-E13*POWER(1+$A$2,$R$2-($Q$2+A13))*POWER(1+$C$2,$S$2-$R$2))*MAX(Dashboard!$C$18,Dashboard!$B$18))))) -> 777.47825
A14: =A13+1 -> 9 | B14: =B13+1/12 -> 18.804795 | C14: =INT(B14)&" y "&ROUND((B14-INT(B14))*12,2)&" m" -> 18 y 9.66 m | D14: =IF(A14>=$E$2,IF(A14<$E$2+$H$2,$P$2,0),IF(B14<Dashboard!$I$6,0,IF(A14>=$F$2,Dashboard!$C$22*POWER(1+$C$2,A14-$F$2),Dashboard!$C$22))) -> 0 | E14: =IF(A14>=$F$2,0,IF(A14=0,Dashboard!$G$10,IF(B14<Dashboard!$I$6,IF($J$2<=Dashboard!$H$10,Dashboard!$H$10,MAX(Dashboard!$H$10,MIN($J$2,Dashboard!$H$10*POWER($J$2/Dashboard!$H$10,A14/$D$2)))),$I$2-D14-Dashboard!$I$10-Dashboard!$J$10-Dashboard!$F$10*$I$2))) -> 531.72623 | F14: =IF(A14>=$F$2,$X$2*POWER(1+$C$2,A14-$F$2)+D14,0) -> 0 | G14: =IF(F14<=0,0,IF(F14*12<=18200,F14,IF(F14*12<=40712,(18200+(F14*12-18200)/0.84)/12,IF(F14*12<=103712,(45000+(F14*12-40712)/0.7)/12,IF(F14*12<=138362,(135000+(F14*12-103712)/0.63)/12,(190000+(F14*12-138362)/0.55)/12))))) -> 0 | H14: =IF(A14=$E$2,$W$2,0) -> 0 | I14: =E14-G14-H14 -> 531.72623 | J14: =IF(A14>=$F$2,$B$2,$A$2) -> 0.0079741404 | K14: =(K13+I14)*(1+J14) -> 113111.57 | L14: =IF(A14>=$F$2,K14,"") | M14: =IF(AND(A14<$E$2,E14>0),E14*POWER(1+$A$2,$E$2-A14),0) -> 2482.389 | N14: =IF(M14<=0,0,IF($E$2-A14<12,(M14-E14)*Dashboard!$B$18,IF($Q$2+A14>=$R$2,MAX(0,M14-E14*POWER(1+$C$2,$E$2-A14))*MAX(Dashboard!$C$18,Dashboard!$B$18),IF($S$2<$R$2,(M14-E14)*0.5*Dashboard!$B$18,(E14*POWER(1+$A$2,$R$2-($Q$2+A14))-E14)*0.5*Dashboard!$B$18+MAX(0,M14-E14*POWER(1+$A$2,$R$2-($Q$2+A14))*POWER(1+$C$2,$S$2-$R$2))*MAX(Dashboard!$C$18,Dashboard!$B$18))))) -> 775.62961
A15: =A14+1 -> 10 | B15: =B14+1/12 -> 18.888128 | C15: =INT(B15)&" y "&ROUND((B15-INT(B15))*12,2)&" m" -> 18 y 10.66 m | D15: =IF(A15>=$E$2,IF(A15<$E$2+$H$2,$P$2,0),IF(B15<Dashboard!$I$6,0,IF(A15>=$F$2,Dashboard!$C$22*POWER(1+$C$2,A15-$F$2),Dashboard!$C$22))) -> 0 | E15: =IF(A15>=$F$2,0,IF(A15=0,Dashboard!$G$10,IF(B15<Dashboard!$I$6,IF($J$2<=Dashboard!$H$10,Dashboard!$H$10,MAX(Dashboard!$H$10,MIN($J$2,Dashboard!$H$10*POWER($J$2/Dashboard!$H$10,A15/$D$2)))),$I$2-D15-Dashboard!$I$10-Dashboard!$J$10-Dashboard!$F$10*$I$2))) -> 535.37337 | F15: =IF(A15>=$F$2,$X$2*POWER(1+$C$2,A15-$F$2)+D15,0) -> 0 | G15: =IF(F15<=0,0,IF(F15*12<=18200,F15,IF(F15*12<=40712,(18200+(F15*12-18200)/0.84)/12,IF(F15*12<=103712,(45000+(F15*12-40712)/0.7)/12,IF(F15*12<=138362,(135000+(F15*12-103712)/0.63)/12,(190000+(F15*12-138362)/0.55)/12))))) -> 0 | H15: =IF(A15=$E$2,$W$2,0) -> 0 | I15: =E15-G15-H15 -> 535.37337 | J15: =IF(A15>=$F$2,$B$2,$A$2) -> 0.0079741404 | K15: =(K14+I15)*(1+J15) -> 114553.18 | L15: =IF(A15>=$F$2,K15,"") | M15: =IF(AND(A15<$E$2,E15>0),E15*POWER(1+$A$2,$E$2-A15),0) -> 2479.6427 | N15: =IF(M15<=0,0,IF($E$2-A15<12,(M15-E15)*Dashboard!$B$18,IF($Q$2+A15>=$R$2,MAX(0,M15-E15*POWER(1+$C$2,$E$2-A15))*MAX(Dashboard!$C$18,Dashboard!$B$18),IF($S$2<$R$2,(M15-E15)*0.5*Dashboard!$B$18,(E15*POWER(1+$A$2,$R$2-($Q$2+A15))-E15)*0.5*Dashboard!$B$18+MAX(0,M15-E15*POWER(1+$A$2,$R$2-($Q$2+A15))*POWER(1+$C$2,$S$2-$R$2))*MAX(Dashboard!$C$18,Dashboard!$B$18))))) -> 773.77624
A16: =A15+1 -> 11 | B16: =B15+1/12 -> 18.971461 | C16: =INT(B16)&" y "&ROUND((B16-INT(B16))*12,2)&" m" -> 18 y 11.66 m | D16: =IF(A16>=$E$2,IF(A16<$E$2+$H$2,$P$2,0),IF(B16<Dashboard!$I$6,0,IF(A16>=$F$2,Dashboard!$C$22*POWER(1+$C$2,A16-$F$2),Dashboard!$C$22))) -> 0 | E16: =IF(A16>=$F$2,0,IF(A16=0,Dashboard!$G$10,IF(B16<Dashboard!$I$6,IF($J$2<=Dashboard!$H$10,Dashboard!$H$10,MAX(Dashboard!$H$10,MIN($J$2,Dashboard!$H$10*POWER($J$2/Dashboard!$H$10,A16/$D$2)))),$I$2-D16-Dashboard!$I$10-Dashboard!$J$10-Dashboard!$F$10*$I$2))) -> 539.04552 | F16: =IF(A16>=$F$2,$X$2*POWER(1+$C$2,A16-$F$2)+D16,0) -> 0 | G16: =IF(F16<=0,0,IF(F16*12<=18200,F16,IF(F16*12<=40712,(18200+(F16*12-18200)/0.84)/12,IF(F16*12<=103712,(45000+(F16*12-40712)/0.7)/12,IF(F16*12<=138362,(135000+(F16*12-103712)/0.63)/12,(190000+(F16*12-138362)/0.55)/12))))) -> 0 | H16: =IF(A16=$E$2,$W$2,0) -> 0 | I16: =E16-G16-H16 -> 539.04552 | J16: =IF(A16>=$F$2,$B$2,$A$2) -> 0.0079741404 | K16: =(K15+I16)*(1+J16) -> 116009.99 | L16: =IF(A16>=$F$2,K16,"") | M16: =IF(AND(A16<$E$2,E16>0),E16*POWER(1+$A$2,$E$2-A16),0) -> 2476.8996 | N16: =IF(M16<=0,0,IF($E$2-A16<12,(M16-E16)*Dashboard!$B$18,IF($Q$2+A16>=$R$2,MAX(0,M16-E16*POWER(1+$C$2,$E$2-A16))*MAX(Dashboard!$C$18,Dashboard!$B$18),IF($S$2<$R$2,(M16-E16)*0.5*Dashboard!$B$18,(E16*POWER(1+$A$2,$R$2-($Q$2+A16))-E16)*0.5*Dashboard!$B$18+MAX(0,M16-E16*POWER(1+$A$2,$R$2-($Q$2+A16))*POWER(1+$C$2,$S$2-$R$2))*MAX(Dashboard!$C$18,Dashboard!$B$18))))) -> 771.91809
A17: =A16+1 -> 12 | B17: =B16+1/12 -> 19.054795 | C17: =INT(B17)&" y "&ROUND((B17-INT(B17))*12,2)&" m" -> 19 y 0.66 m | D17: =IF(A17>=$E$2,IF(A17<$E$2+$H$2,$P$2,0),IF(B17<Dashboard!$I$6,0,IF(A17>=$F$2,Dashboard!$C$22*POWER(1+$C$2,A17-$F$2),Dashboard!$C$22))) -> 0 | E17: =IF(A17>=$F$2,0,IF(A17=0,Dashboard!$G$10,IF(B17<Dashboard!$I$6,IF($J$2<=Dashboard!$H$10,Dashboard!$H$10,MAX(Dashboard!$H$10,MIN($J$2,Dashboard!$H$10*POWER($J$2/Dashboard!$H$10,A17/$D$2)))),$I$2-D17-Dashboard!$I$10-Dashboard!$J$10-Dashboard!$F$10*$I$2))) -> 542.74285 | F17: =IF(A17>=$F$2,$X$2*POWER(1+$C$2,A17-$F$2)+D17,0) -> 0 | G17: =IF(F17<=0,0,IF(F17*12<=18200,F17,IF(F17*12<=40712,(18200+(F17*12-18200)/0.84)/12,IF(F17*12<=103712,(45000+(F17*12-40712)/0.7)/12,IF(F17*12<=138362,(135000+(F17*12-103712)/0.63)/12,(190000+(F17*12-138362)/0.55)/12))))) -> 0 | H17: =IF(A17=$E$2,$W$2,0) -> 0 | I17: =E17-G17-H17 -> 542.74285 | J17: =IF(A17>=$F$2,$B$2,$A$2) -> 0.0079741404 | K17: =(K16+I17)*(1+J17) -> 117482.14 | L17: =IF(A17>=$F$2,K17,"") | M17: =IF(AND(A17<$E$2,E17>0),E17*POWER(1+$A$2,$E$2-A17),0) -> 2474.1595 | N17: =IF(M17<=0,0,IF($E$2-A17<12,(M17-E17)*Dashboard!$B$18,IF($Q$2+A17>=$R$2,MAX(0,M17-E17*POWER(1+$C$2,$E$2-A17))*MAX(Dashboard!$C$18,Dashboard!$B$18),IF($S$2<$R$2,(M17-E17)*0.5*Dashboard!$B$18,(E17*POWER(1+$A$2,$R$2-($Q$2+A17))-E17)*0.5*Dashboard!$B$18+MAX(0,M17-E17*POWER(1+$A$2,$R$2-($Q$2+A17))*POWER(1+$C$2,$S$2-$R$2))*MAX(Dashboard!$C$18,Dashboard!$B$18))))) -> 770.05513
... A688: =A687+1 -> 683 | B688: =B687+1/12 -> 74.971461 | C688: =INT(B688)&" y "&ROUND((B688-INT(B688))*12,2)&" m" -> 74 y 11.66 m | D688: =IF(A688>=$E$2,IF(A688<$E$2+$H$2,$P$2,0),IF(B688<Dashboard!$I$6,0,IF(A688>=$F$2,Dashboard!$C$22*POWER(1+$C$2,A688-$F$2),Dashboard!$C$22))) -> 0 | E688: =IF(A688>=$F$2,0,IF(A688=0,Dashboard!$G$10,IF(B688<Dashboard!$I$6,IF($J$2<=Dashboard!$H$10,Dashboard!$H$10,MAX(Dashboard!$H$10,MIN($J$2,Dashboard!$H$10*POWER($J$2/Dashboard!$H$10,A688/$D$2)))),$I$2-D688-Dashboard!$I$10-Dashboard!$J$10-Dashboard!$F$10*$I$2))) -> 0 | F688: =IF(A688>=$F$2,$X$2*POWER(1+$C$2,A688-$F$2)+D688,0) -> 11717.297 | G688: =IF(F688<=0,0,IF(F688*12<=18200,F688,IF(F688*12<=40712,(18200+(F688*12-18200)/0.84)/12,IF(F688*12<=103712,(45000+(F688*12-40712)/0.7)/12,IF(F688*12<=138362,(135000+(F688*12-103712)/0.63)/12,(190000+(F688*12-138362)/0.55)/12))))) -> 16173.571 | H688: =IF(A688=$E$2,$W$2,0) -> 0 | I688: =E688-G688-H688 -> -16173.571 | J688: =IF(A688>=$F$2,$B$2,$A$2) -> 0.0079741404 | K688: =(K687+I688)*(1+J688) -> 38600578 | L688: =IF(A688>=$F$2,K688,"") -> 38600578 | M688: =IF(AND(A688<$E$2,E688>0),E688*POWER(1+$A$2,$E$2-A688),0) -> 0 | N688: =IF(M688<=0,0,IF($E$2-A688<12,(M688-E688)*Dashboard!$B$18,IF($Q$2+A688>=$R$2,MAX(0,M688-E688*POWER(1+$C$2,$E$2-A688))*MAX(Dashboard!$C$18,Dashboard!$B$18),IF($S$2<$R$2,(M688-E688)*0.5*Dashboard!$B$18,(E688*POWER(1+$A$2,$R$2-($Q$2+A688))-E688)*0.5*Dashboard!$B$18+MAX(0,M688-E688*POWER(1+$A$2,$R$2-($Q$2+A688))*POWER(1+$C$2,$S$2-$R$2))*MAX(Dashboard!$C$18,Dashboard!$B$18))))) -> 0

Sheet Calc2
A1: gm /mo | B1: post /mo | C1: cpi /mo | D1: M ramp | E1: S buy | F1: S retire | G1: S final | H1: n mort | I1: afterTax/mo | J1: target inv | K1: inv rent | L1: inv mort | M1: inv paid | N1: deposit | O1: loan | P1: repayment | Q1: start abs | R1: cutoff abs | S1: sale abs | T1: tot value | U1: tot tax | V1: gross factor | W1: gross w/d | X1: needs base
A2: =(1+Dashboard!$B$10)^(1/12)-1 -> 0.0079741404 | B2: =(1+Dashboard!$C$10)^(1/12)-1 -> 0.0079741404 | C2: =(1+Dashboard!$E$10)^(1/12)-1 -> 0.0020598363 | D2: =MAX(1,ROUND((Dashboard!$I$6-Dashboard!$F$6)*12,0)) -> 83 | E2: =MAX(1,ROUND((Dashboard!$D$23-Dashboard!$F$6)*12,0)) -> 83 | F2: =MAX(1,ROUND((Dashboard!$F$23-Dashboard!$F$6)*12,0)) -> 383 | G2: =ROUND((Dashboard!$J$6-Dashboard!$F$6)*12,0) -> 503 | H2: =Dashboard!$E$23*12 -> 360 | I2: =Dashboard!$E$6 -> 13202 | J2: =$I$2-IF(Dashboard!$D$23<=Dashboard!$I$6,$P$2,Dashboard!$C$23)-Dashboard!$I$10-Dashboard!$J$10-Dashboard!$F$10*$I$2 -> 1789.4325 | K2: =$I$2-Dashboard!$C$23-Dashboard!$I$10-Dashboard!$J$10-Dashboard!$F$10*$I$2 -> 6881.8 | L2: =$I$2-$P$2-Dashboard!$I$10-Dashboard!$J$10-Dashboard!$F$10*$I$2 -> 1789.4325 | M2: =$I$2-Dashboard!$I$10-Dashboard!$J$10-Dashboard!$F$10*$I$2 -> 6881.8 | N2: =Dashboard!$G$23*Dashboard!$H$23 -> 44703.378 | O2: =Dashboard!$G$23-$N$2 -> 849364.19 | P2: =IF(OR($O$2<=0,$H$2<=0),0,-PMT(Dashboard!$D$10/12,$H$2,$O$2)) -> 5092.3675 | Q2: =Dashboard!$G$6*12+Dashboard!$H$6-1 -> 24306 | R2: =Dashboard!$D$18*12+Dashboard!$E$18-1 -> 24330 | S2: =$Q$2+$E$2 -> 24389 | T2: =SUM($M$5:$M$688) -> 302847.37 | U2: =SUM($N$5:$N$688) -> 41243.542 | V2: =IF($T$2-$U$2>0,$T$2/($T$2-$U$2),1) -> 1.1576565 | W2: =$N$2*$V$2*Dashboard!$I$23 -> 51751.156 | X2: =Dashboard!$I$10+Dashboard!$J$10+Dashboard!$F$10*$I$2 -> 6320.2
A4: Period | B4: Age | C4: Age label | D4: Housing | E4: Contribution | F4: Need (after-tax) | G4: Drawdown (pre-tax) | H4: Purchase w/d | I4: Net flow | J4: Rate /mo | K4: Portfolio | L4: Post-ret balance | M4: Parcel value @ sale | N4: Parcel CGT
A5: 0 | B5: =Dashboard!$F$6 -> 18.054795 | C5: =INT(B5)&" y "&ROUND((B5-INT(B5))*12,2)&" m" -> 18 y 0.66 m | D5: =IF(A5>=$E$2,IF(A5<$E$2+$H$2,$P$2,0),IF(B5<Dashboard!$I$6,0,IF(A5>=$F$2,Dashboard!$C$23*POWER(1+$C$2,A5-$F$2),Dashboard!$C$23))) -> 0 | E5: =IF(A5>=$F$2,0,IF(A5=0,Dashboard!$G$10,IF(B5<Dashboard!$I$6,IF($J$2<=Dashboard!$H$10,Dashboard!$H$10,MAX(Dashboard!$H$10,MIN($J$2,Dashboard!$H$10*POWER($J$2/Dashboard!$H$10,A5/$D$2)))),$I$2-D5-Dashboard!$I$10-Dashboard!$J$10-Dashboard!$F$10*$I$2))) -> 100000 | F5: =IF(A5>=$F$2,$X$2*POWER(1+$C$2,A5-$F$2)+D5,0) -> 0 | G5: =IF(F5<=0,0,IF(F5*12<=18200,F5,IF(F5*12<=40712,(18200+(F5*12-18200)/0.84)/12,IF(F5*12<=103712,(45000+(F5*12-40712)/0.7)/12,IF(F5*12<=138362,(135000+(F5*12-103712)/0.63)/12,(190000+(F5*12-138362)/0.55)/12))))) -> 0 | H5: =IF(A5=$E$2,$W$2,0) -> 0 | I5: =E5-G5-H5 -> 100000 | J5: =IF(A5>=$F$2,$B$2,$A$2) -> 0.0079741404 | K5: =I5*(1+J5) -> 100797.41 | L5: =IF(A5>=$F$2,K5,"") | M5: =IF(AND(A5<$E$2,E5>0),E5*POWER(1+$A$2,$E$2-A5),0) -> 193330.07 | N5: =IF(M5<=0,0,IF($E$2-A5<12,(M5-E5)*Dashboard!$B$18,IF($Q$2+A5>=$R$2,MAX(0,M5-E5*POWER(1+$C$2,$E$2-A5))*MAX(Dashboard!$C$18,Dashboard!$B$18),IF($S$2<$R$2,(M5-E5)*0.5*Dashboard!$B$18,(E5*POWER(1+$A$2,$R$2-($Q$2+A5))-E5)*0.5*Dashboard!$B$18+MAX(0,M5-E5*POWER(1+$A$2,$R$2-($Q$2+A5))*POWER(1+$C$2,$S$2-$R$2))*MAX(Dashboard!$C$18,Dashboard!$B$18))))) -> 31589.211
A6: =A5+1 -> 1 | B6: =B5+1/12 -> 18.138128 | C6: =INT(B6)&" y "&ROUND((B6-INT(B6))*12,2)&" m" -> 18 y 1.66 m | D6: =IF(A6>=$E$2,IF(A6<$E$2+$H$2,$P$2,0),IF(B6<Dashboard!$I$6,0,IF(A6>=$F$2,Dashboard!$C$23*POWER(1+$C$2,A6-$F$2),Dashboard!$C$23))) -> 0 | E6: =IF(A6>=$F$2,0,IF(A6=0,Dashboard!$G$10,IF(B6<Dashboard!$I$6,IF($J$2<=Dashboard!$H$10,Dashboard!$H$10,MAX(Dashboard!$H$10,MIN($J$2,Dashboard!$H$10*POWER($J$2/Dashboard!$H$10,A6/$D$2)))),$I$2-D6-Dashboard!$I$10-Dashboard!$J$10-Dashboard!$F$10*$I$2))) -> 507.7403 | F6: =IF(A6>=$F$2,$X$2*POWER(1+$C$2,A6-$F$2)+D6,0) -> 0 | G6: =IF(F6<=0,0,IF(F6*12<=18200,F6,IF(F6*12<=40712,(18200+(F6*12-18200)/0.84)/12,IF(F6*12<=103712,(45000+(F6*12-40712)/0.7)/12,IF(F6*12<=138362,(135000+(F6*12-103712)/0.63)/12,(190000+(F6*12-138362)/0.55)/12))))) -> 0 | H6: =IF(A6=$E$2,$W$2,0) -> 0 | I6: =E6-G6-H6 -> 507.7403 | J6: =IF(A6>=$F$2,$B$2,$A$2) -> 0.0079741404 | K6: =(K5+I6)*(1+J6) -> 102112.98 | L6: =IF(A6>=$F$2,K6,"") | M6: =IF(AND(A6<$E$2,E6>0),E6*POWER(1+$A$2,$E$2-A6),0) -> 973.84906 | N6: =IF(M6<=0,0,IF($E$2-A6<12,(M6-E6)*Dashboard!$B$18,IF($Q$2+A6>=$R$2,MAX(0,M6-E6*POWER(1+$C$2,$E$2-A6))*MAX(Dashboard!$C$18,Dashboard!$B$18),IF($S$2<$R$2,(M6-E6)*0.5*Dashboard!$B$18,(E6*POWER(1+$A$2,$R$2-($Q$2+A6))-E6)*0.5*Dashboard!$B$18+MAX(0,M6-E6*POWER(1+$A$2,$R$2-($Q$2+A6))*POWER(1+$C$2,$S$2-$R$2))*MAX(Dashboard!$C$18,Dashboard!$B$18))))) -> 158.17835
A7: =A6+1 -> 2 | B7: =B6+1/12 -> 18.221461 | C7: =INT(B7)&" y "&ROUND((B7-INT(B7))*12,2)&" m" -> 18 y 2.66 m | D7: =IF(A7>=$E$2,IF(A7<$E$2+$H$2,$P$2,0),IF(B7<Dashboard!$I$6,0,IF(A7>=$F$2,Dashboard!$C$23*POWER(1+$C$2,A7-$F$2),Dashboard!$C$23))) -> 0 | E7: =IF(A7>=$F$2,0,IF(A7=0,Dashboard!$G$10,IF(B7<Dashboard!$I$6,IF($J$2<=Dashboard!$H$10,Dashboard!$H$10,MAX(Dashboard!$H$10,MIN($J$2,Dashboard!$H$10*POWER($J$2/Dashboard!$H$10,A7/$D$2)))),$I$2-D7-Dashboard!$I$10-Dashboard!$J$10-Dashboard!$F$10*$I$2))) -> 515.60042 | F7: =IF(A7>=$F$2,$X$2*POWER(1+$C$2,A7-$F$2)+D7,0) -> 0 | G7: =IF(F7<=0,0,IF(F7*12<=18200,F7,IF(F7*12<=40712,(18200+(F7*12-18200)/0.84)/12,IF(F7*12<=103712,(45000+(F7*12-40712)/0.7)/12,IF(F7*12<=138362,(135000+(F7*12-103712)/0.63)/12,(190000+(F7*12-138362)/0.55)/12))))) -> 0 | H7: =IF(A7=$E$2,$W$2,0) -> 0 | I7: =E7-G7-H7 -> 515.60042 | J7: =IF(A7>=$F$2,$B$2,$A$2) -> 0.0079741404 | K7: =(K6+I7)*(1+J7) -> 103446.95 | L7: =IF(A7>=$F$2,K7,"") | M7: =IF(AND(A7<$E$2,E7>0),E7*POWER(1+$A$2,$E$2-A7),0) -> 981.10139 | N7: =IF(M7<=0,0,IF($E$2-A7<12,(M7-E7)*Dashboard!$B$18,IF($Q$2+A7>=$R$2,MAX(0,M7-E7*POWER(1+$C$2,$E$2-A7))*MAX(Dashboard!$C$18,Dashboard!$B$18),IF($S$2<$R$2,(M7-E7)*0.5*Dashboard!$B$18,(E7*POWER(1+$A$2,$R$2-($Q$2+A7))-E7)*0.5*Dashboard!$B$18+MAX(0,M7-E7*POWER(1+$A$2,$R$2-($Q$2+A7))*POWER(1+$C$2,$S$2-$R$2))*MAX(Dashboard!$C$18,Dashboard!$B$18))))) -> 158.39777
A8: =A7+1 -> 3 | B8: =B7+1/12 -> 18.304795 | C8: =INT(B8)&" y "&ROUND((B8-INT(B8))*12,2)&" m" -> 18 y 3.66 m | D8: =IF(A8>=$E$2,IF(A8<$E$2+$H$2,$P$2,0),IF(B8<Dashboard!$I$6,0,IF(A8>=$F$2,Dashboard!$C$23*POWER(1+$C$2,A8-$F$2),Dashboard!$C$23))) -> 0 | E8: =IF(A8>=$F$2,0,IF(A8=0,Dashboard!$G$10,IF(B8<Dashboard!$I$6,IF($J$2<=Dashboard!$H$10,Dashboard!$H$10,MAX(Dashboard!$H$10,MIN($J$2,Dashboard!$H$10*POWER($J$2/Dashboard!$H$10,A8/$D$2)))),$I$2-D8-Dashboard!$I$10-Dashboard!$J$10-Dashboard!$F$10*$I$2))) -> 523.58223 | F8: =IF(A8>=$F$2,$X$2*POWER(1+$C$2,A8-$F$2)+D8,0) -> 0 | G8: =IF(F8<=0,0,IF(F8*12<=18200,F8,IF(F8*12<=40712,(18200+(F8*12-18200)/0.84)/12,IF(F8*12<=103712,(45000+(F8*12-40712)/0.7)/12,IF(F8*12<=138362,(135000+(F8*12-103712)/0.63)/12,(190000+(F8*12-138362)/0.55)/12))))) -> 0 | H8: =IF(A8=$E$2,$W$2,0) -> 0 | I8: =E8-G8-H8 -> 523.58223 | J8: =IF(A8>=$F$2,$B$2,$A$2) -> 0.0079741404 | K8: =(K7+I8)*(1+J8) -> 104799.61 | L8: =IF(A8>=$F$2,K8,"") | M8: =IF(AND(A8<$E$2,E8>0),E8*POWER(1+$A$2,$E$2-A8),0) -> 988.40772 | N8: =IF(M8<=0,0,IF($E$2-A8<12,(M8-E8)*Dashboard!$B$18,IF($Q$2+A8>=$R$2,MAX(0,M8-E8*POWER(1+$C$2,$E$2-A8))*MAX(Dashboard!$C$18,Dashboard!$B$18),IF($S$2<$R$2,(M8-E8)*0.5*Dashboard!$B$18,(E8*POWER(1+$A$2,$R$2-($Q$2+A8))-E8)*0.5*Dashboard!$B$18+MAX(0,M8-E8*POWER(1+$A$2,$R$2-($Q$2+A8))*POWER(1+$C$2,$S$2-$R$2))*MAX(Dashboard!$C$18,Dashboard!$B$18))))) -> 158.60398
A9: =A8+1 -> 4 | B9: =B8+1/12 -> 18.388128 | C9: =INT(B9)&" y "&ROUND((B9-INT(B9))*12,2)&" m" -> 18 y 4.66 m | D9: =IF(A9>=$E$2,IF(A9<$E$2+$H$2,$P$2,0),IF(B9<Dashboard!$I$6,0,IF(A9>=$F$2,Dashboard!$C$23*POWER(1+$C$2,A9-$F$2),Dashboard!$C$23))) -> 0 | E9: =IF(A9>=$F$2,0,IF(A9=0,Dashboard!$G$10,IF(B9<Dashboard!$I$6,IF($J$2<=Dashboard!$H$10,Dashboard!$H$10,MAX(Dashboard!$H$10,MIN($J$2,Dashboard!$H$10*POWER($J$2/Dashboard!$H$10,A9/$D$2)))),$I$2-D9-Dashboard!$I$10-Dashboard!$J$10-Dashboard!$F$10*$I$2))) -> 531.68759 | F9: =IF(A9>=$F$2,$X$2*POWER(1+$C$2,A9-$F$2)+D9,0) -> 0 | G9: =IF(F9<=0,0,IF(F9*12<=18200,F9,IF(F9*12<=40712,(18200+(F9*12-18200)/0.84)/12,IF(F9*12<=103712,(45000+(F9*12-40712)/0.7)/12,IF(F9*12<=138362,(135000+(F9*12-103712)/0.63)/12,(190000+(F9*12-138362)/0.55)/12))))) -> 0 | H9: =IF(A9=$E$2,$W$2,0) -> 0 | I9: =E9-G9-H9 -> 531.68759 | J9: =IF(A9>=$F$2,$B$2,$A$2) -> 0.0079741404 | K9: =(K8+I9)*(1+J9) -> 106171.22 | L9: =IF(A9>=$F$2,K9,"") | M9: =IF(AND(A9<$E$2,E9>0),E9*POWER(1+$A$2,$E$2-A9),0) -> 995.76847 | N9: =IF(M9<=0,0,IF($E$2-A9<12,(M9-E9)*Dashboard!$B$18,IF($Q$2+A9>=$R$2,MAX(0,M9-E9*POWER(1+$C$2,$E$2-A9))*MAX(Dashboard!$C$18,Dashboard!$B$18),IF($S$2<$R$2,(M9-E9)*0.5*Dashboard!$B$18,(E9*POWER(1+$A$2,$R$2-($Q$2+A9))-E9)*0.5*Dashboard!$B$18+MAX(0,M9-E9*POWER(1+$A$2,$R$2-($Q$2+A9))*POWER(1+$C$2,$S$2-$R$2))*MAX(Dashboard!$C$18,Dashboard!$B$18))))) -> 158.79665
A10: =A9+1 -> 5 | B10: =B9+1/12 -> 18.471461 | C10: =INT(B10)&" y "&ROUND((B10-INT(B10))*12,2)&" m" -> 18 y 5.66 m | D10: =IF(A10>=$E$2,IF(A10<$E$2+$H$2,$P$2,0),IF(B10<Dashboard!$I$6,0,IF(A10>=$F$2,Dashboard!$C$23*POWER(1+$C$2,A10-$F$2),Dashboard!$C$23))) -> 0 | E10: =IF(A10>=$F$2,0,IF(A10=0,Dashboard!$G$10,IF(B10<Dashboard!$I$6,IF($J$2<=Dashboard!$H$10,Dashboard!$H$10,MAX(Dashboard!$H$10,MIN($J$2,Dashboard!$H$10*POWER($J$2/Dashboard!$H$10,A10/$D$2)))),$I$2-D10-Dashboard!$I$10-Dashboard!$J$10-Dashboard!$F$10*$I$2))) -> 539.91844 | F10: =IF(A10>=$F$2,$X$2*POWER(1+$C$2,A10-$F$2)+D10,0) -> 0 | G10: =IF(F10<=0,0,IF(F10*12<=18200,F10,IF(F10*12<=40712,(18200+(F10*12-18200)/0.84)/12,IF(F10*12<=103712,(45000+(F10*12-40712)/0.7)/12,IF(F10*12<=138362,(135000+(F10*12-103712)/0.63)/12,(190000+(F10*12-138362)/0.55)/12))))) -> 0 | H10: =IF(A10=$E$2,$W$2,0) -> 0 | I10: =E10-G10-H10 -> 539.91844 | J10: =IF(A10>=$F$2,$B$2,$A$2) -> 0.0079741404 | K10: =(K9+I10)*(1+J10) -> 107562.07 | L10: =IF(A10>=$F$2,K10,"") | M10: =IF(AND(A10<$E$2,E10>0),E10*POWER(1+$A$2,$E$2-A10),0) -> 1003.184 | N10: =IF(M10<=0,0,IF($E$2-A10<12,(M10-E10)*Dashboard!$B$18,IF($Q$2+A10>=$R$2,MAX(0,M10-E10*POWER(1+$C$2,$E$2-A10))*MAX(Dashboard!$C$18,Dashboard!$B$18),IF($S$2<$R$2,(M10-E10)*0.5*Dashboard!$B$18,(E10*POWER(1+$A$2,$R$2-($Q$2+A10))-E10)*0.5*Dashboard!$B$18+MAX(0,M10-E10*POWER(1+$A$2,$R$2-($Q$2+A10))*POWER(1+$C$2,$S$2-$R$2))*MAX(Dashboard!$C$18,Dashboard!$B$18))))) -> 158.97546
A11: =A10+1 -> 6 | B11: =B10+1/12 -> 18.554795 | C11: =INT(B11)&" y "&ROUND((B11-INT(B11))*12,2)&" m" -> 18 y 6.66 m | D11: =IF(A11>=$E$2,IF(A11<$E$2+$H$2,$P$2,0),IF(B11<Dashboard!$I$6,0,IF(A11>=$F$2,Dashboard!$C$23*POWER(1+$C$2,A11-$F$2),Dashboard!$C$23))) -> 0 | E11: =IF(A11>=$F$2,0,IF(A11=0,Dashboard!$G$10,IF(B11<Dashboard!$I$6,IF($J$2<=Dashboard!$H$10,Dashboard!$H$10,MAX(Dashboard!$H$10,MIN($J$2,Dashboard!$H$10*POWER($J$2/Dashboard!$H$10,A11/$D$2)))),$I$2-D11-Dashboard!$I$10-Dashboard!$J$10-Dashboard!$F$10*$I$2))) -> 548.2767 | F11: =IF(A11>=$F$2,$X$2*POWER(1+$C$2,A11-$F$2)+D11,0) -> 0 | G11: =IF(F11<=0,0,IF(F11*12<=18200,F11,IF(F11*12<=40712,(18200+(F11*12-18200)/0.84)/12,IF(F11*12<=103712,(45000+(F11*12-40712)/0.7)/12,IF(F11*12<=138362,(135000+(F11*12-103712)/0.63)/12,(190000+(F11*12-138362)/0.55)/12))))) -> 0 | H11: =IF(A11=$E$2,$W$2,0) -> 0 | I11: =E11-G11-H11 -> 548.2767 | J11: =IF(A11>=$F$2,$B$2,$A$2) -> 0.0079741404 | K11: =(K10+I11)*(1+J11) -> 108972.43 | L11: =IF(A11>=$F$2,K11,"") | M11: =IF(AND(A11<$E$2,E11>0),E11*POWER(1+$A$2,$E$2-A11),0) -> 1010.6548 | N11: =IF(M11<=0,0,IF($E$2-A11<12,(M11-E11)*Dashboard!$B$18,IF($Q$2+A11>=$R$2,MAX(0,M11-E11*POWER(1+$C$2,$E$2-A11))*MAX(Dashboard!$C$18,Dashboard!$B$18),IF($S$2<$R$2,(M11-E11)*0.5*Dashboard!$B$18,(E11*POWER(1+$A$2,$R$2-($Q$2+A11))-E11)*0.5*Dashboard!$B$18+MAX(0,M11-E11*POWER(1+$A$2,$R$2-($Q$2+A11))*POWER(1+$C$2,$S$2-$R$2))*MAX(Dashboard!$C$18,Dashboard!$B$18))))) -> 159.14006
A12: =A11+1 -> 7 | B12: =B11+1/12 -> 18.638128 | C12: =INT(B12)&" y "&ROUND((B12-INT(B12))*12,2)&" m" -> 18 y 7.66 m | D12: =IF(A12>=$E$2,IF(A12<$E$2+$H$2,$P$2,0),IF(B12<Dashboard!$I$6,0,IF(A12>=$F$2,Dashboard!$C$23*POWER(1+$C$2,A12-$F$2),Dashboard!$C$23))) -> 0 | E12: =IF(A12>=$F$2,0,IF(A12=0,Dashboard!$G$10,IF(B12<Dashboard!$I$6,IF($J$2<=Dashboard!$H$10,Dashboard!$H$10,MAX(Dashboard!$H$10,MIN($J$2,Dashboard!$H$10*POWER($J$2/Dashboard!$H$10,A12/$D$2)))),$I$2-D12-Dashboard!$I$10-Dashboard!$J$10-Dashboard!$F$10*$I$2))) -> 556.76435 | F12: =IF(A12>=$F$2,$X$2*POWER(1+$C$2,A12-$F$2)+D12,0) -> 0 | G12: =IF(F12<=0,0,IF(F12*12<=18200,F12,IF(F12*12<=40712,(18200+(F12*12-18200)/0.84)/12,IF(F12*12<=103712,(45000+(F12*12-40712)/0.7)/12,IF(F12*12<=138362,(135000+(F12*12-103712)/0.63)/12,(190000+(F12*12-138362)/0.55)/12))))) -> 0 | H12: =IF(A12=$E$2,$W$2,0) -> 0 | I12: =E12-G12-H12 -> 556.76435 | J12: =IF(A12>=$F$2,$B$2,$A$2) -> 0.0079741404 | K12: =(K11+I12)*(1+J12) -> 110402.6 | L12: =IF(A12>=$F$2,K12,"") | M12: =IF(AND(A12<$E$2,E12>0),E12*POWER(1+$A$2,$E$2-A12),0) -> 1018.1812 | N12: =IF(M12<=0,0,IF($E$2-A12<12,(M12-E12)*Dashboard!$B$18,IF($Q$2+A12>=$R$2,MAX(0,M12-E12*POWER(1+$C$2,$E$2-A12))*MAX(Dashboard!$C$18,Dashboard!$B$18),IF($S$2<$R$2,(M12-E12)*0.5*Dashboard!$B$18,(E12*POWER(1+$A$2,$R$2-($Q$2+A12))-E12)*0.5*Dashboard!$B$18+MAX(0,M12-E12*POWER(1+$A$2,$R$2-($Q$2+A12))*POWER(1+$C$2,$S$2-$R$2))*MAX(Dashboard!$C$18,Dashboard!$B$18))))) -> 159.29011
A13: =A12+1 -> 8 | B13: =B12+1/12 -> 18.721461 | C13: =INT(B13)&" y "&ROUND((B13-INT(B13))*12,2)&" m" -> 18 y 8.66 m | D13: =IF(A13>=$E$2,IF(A13<$E$2+$H$2,$P$2,0),IF(B13<Dashboard!$I$6,0,IF(A13>=$F$2,Dashboard!$C$23*POWER(1+$C$2,A13-$F$2),Dashboard!$C$23))) -> 0 | E13: =IF(A13>=$F$2,0,IF(A13=0,Dashboard!$G$10,IF(B13<Dashboard!$I$6,IF($J$2<=Dashboard!$H$10,Dashboard!$H$10,MAX(Dashboard!$H$10,MIN($J$2,Dashboard!$H$10*POWER($J$2/Dashboard!$H$10,A13/$D$2)))),$I$2-D13-Dashboard!$I$10-Dashboard!$J$10-Dashboard!$F$10*$I$2))) -> 565.38339 | F13: =IF(A13>=$F$2,$X$2*POWER(1+$C$2,A13-$F$2)+D13,0) -> 0 | G13: =IF(F13<=0,0,IF(F13*12<=18200,F13,IF(F13*12<=40712,(18200+(F13*12-18200)/0.84)/12,IF(F13*12<=103712,(45000+(F13*12-40712)/0.7)/12,IF(F13*12<=138362,(135000+(F13*12-103712)/0.63)/12,(190000+(F13*12-138362)/0.55)/12))))) -> 0 | H13: =IF(A13=$E$2,$W$2,0) -> 0 | I13: =E13-G13-H13 -> 565.38339 | J13: =IF(A13>=$F$2,$B$2,$A$2) -> 0.0079741404 | K13: =(K12+I13)*(1+J13) -> 111852.86 | L13: =IF(A13>=$F$2,K13,"") | M13: =IF(AND(A13<$E$2,E13>0),E13*POWER(1+$A$2,$E$2-A13),0) -> 1025.7637 | N13: =IF(M13<=0,0,IF($E$2-A13<12,(M13-E13)*Dashboard!$B$18,IF($Q$2+A13>=$R$2,MAX(0,M13-E13*POWER(1+$C$2,$E$2-A13))*MAX(Dashboard!$C$18,Dashboard!$B$18),IF($S$2<$R$2,(M13-E13)*0.5*Dashboard!$B$18,(E13*POWER(1+$A$2,$R$2-($Q$2+A13))-E13)*0.5*Dashboard!$B$18+MAX(0,M13-E13*POWER(1+$A$2,$R$2-($Q$2+A13))*POWER(1+$C$2,$S$2-$R$2))*MAX(Dashboard!$C$18,Dashboard!$B$18))))) -> 159.42525
A14: =A13+1 -> 9 | B14: =B13+1/12 -> 18.804795 | C14: =INT(B14)&" y "&ROUND((B14-INT(B14))*12,2)&" m" -> 18 y 9.66 m | D14: =IF(A14>=$E$2,IF(A14<$E$2+$H$2,$P$2,0),IF(B14<Dashboard!$I$6,0,IF(A14>=$F$2,Dashboard!$C$23*POWER(1+$C$2,A14-$F$2),Dashboard!$C$23))) -> 0 | E14: =IF(A14>=$F$2,0,IF(A14=0,Dashboard!$G$10,IF(B14<Dashboard!$I$6,IF($J$2<=Dashboard!$H$10,Dashboard!$H$10,MAX(Dashboard!$H$10,MIN($J$2,Dashboard!$H$10*POWER($J$2/Dashboard!$H$10,A14/$D$2)))),$I$2-D14-Dashboard!$I$10-Dashboard!$J$10-Dashboard!$F$10*$I$2))) -> 574.13587 | F14: =IF(A14>=$F$2,$X$2*POWER(1+$C$2,A14-$F$2)+D14,0) -> 0 | G14: =IF(F14<=0,0,IF(F14*12<=18200,F14,IF(F14*12<=40712,(18200+(F14*12-18200)/0.84)/12,IF(F14*12<=103712,(45000+(F14*12-40712)/0.7)/12,IF(F14*12<=138362,(135000+(F14*12-103712)/0.63)/12,(190000+(F14*12-138362)/0.55)/12))))) -> 0 | H14: =IF(A14=$E$2,$W$2,0) -> 0 | I14: =E14-G14-H14 -> 574.13587 | J14: =IF(A14>=$F$2,$B$2,$A$2) -> 0.0079741404 | K14: =(K13+I14)*(1+J14) -> 113323.5 | L14: =IF(A14>=$F$2,K14,"") | M14: =IF(AND(A14<$E$2,E14>0),E14*POWER(1+$A$2,$E$2-A14),0) -> 1033.4026 | N14: =IF(M14<=0,0,IF($E$2-A14<12,(M14-E14)*Dashboard!$B$18,IF($Q$2+A14>=$R$2,MAX(0,M14-E14*POWER(1+$C$2,$E$2-A14))*MAX(Dashboard!$C$18,Dashboard!$B$18),IF($S$2<$R$2,(M14-E14)*0.5*Dashboard!$B$18,(E14*POWER(1+$A$2,$R$2-($Q$2+A14))-E14)*0.5*Dashboard!$B$18+MAX(0,M14-E14*POWER(1+$A$2,$R$2-($Q$2+A14))*POWER(1+$C$2,$S$2-$R$2))*MAX(Dashboard!$C$18,Dashboard!$B$18))))) -> 159.54513
A15: =A14+1 -> 10 | B15: =B14+1/12 -> 18.888128 | C15: =INT(B15)&" y "&ROUND((B15-INT(B15))*12,2)&" m" -> 18 y 10.66 m | D15: =IF(A15>=$E$2,IF(A15<$E$2+$H$2,$P$2,0),IF(B15<Dashboard!$I$6,0,IF(A15>=$F$2,Dashboard!$C$23*POWER(1+$C$2,A15-$F$2),Dashboard!$C$23))) -> 0 | E15: =IF(A15>=$F$2,0,IF(A15=0,Dashboard!$G$10,IF(B15<Dashboard!$I$6,IF($J$2<=Dashboard!$H$10,Dashboard!$H$10,MAX(Dashboard!$H$10,MIN($J$2,Dashboard!$H$10*POWER($J$2/Dashboard!$H$10,A15/$D$2)))),$I$2-D15-Dashboard!$I$10-Dashboard!$J$10-Dashboard!$F$10*$I$2))) -> 583.02383 | F15: =IF(A15>=$F$2,$X$2*POWER(1+$C$2,A15-$F$2)+D15,0) -> 0 | G15: =IF(F15<=0,0,IF(F15*12<=18200,F15,IF(F15*12<=40712,(18200+(F15*12-18200)/0.84)/12,IF(F15*12<=103712,(45000+(F15*12-40712)/0.7)/12,IF(F15*12<=138362,(135000+(F15*12-103712)/0.63)/12,(190000+(F15*12-138362)/0.55)/12))))) -> 0 | H15: =IF(A15=$E$2,$W$2,0) -> 0 | I15: =E15-G15-H15 -> 583.02383 | J15: =IF(A15>=$F$2,$B$2,$A$2) -> 0.0079741404 | K15: =(K14+I15)*(1+J15) -> 114814.83 | L15: =IF(A15>=$F$2,K15,"") | M15: =IF(AND(A15<$E$2,E15>0),E15*POWER(1+$A$2,$E$2-A15),0) -> 1041.0985 | N15: =IF(M15<=0,0,IF($E$2-A15<12,(M15-E15)*Dashboard!$B$18,IF($Q$2+A15>=$R$2,MAX(0,M15-E15*POWER(1+$C$2,$E$2-A15))*MAX(Dashboard!$C$18,Dashboard!$B$18),IF($S$2<$R$2,(M15-E15)*0.5*Dashboard!$B$18,(E15*POWER(1+$A$2,$R$2-($Q$2+A15))-E15)*0.5*Dashboard!$B$18+MAX(0,M15-E15*POWER(1+$A$2,$R$2-($Q$2+A15))*POWER(1+$C$2,$S$2-$R$2))*MAX(Dashboard!$C$18,Dashboard!$B$18))))) -> 159.64938
A16: =A15+1 -> 11 | B16: =B15+1/12 -> 18.971461 | C16: =INT(B16)&" y "&ROUND((B16-INT(B16))*12,2)&" m" -> 18 y 11.66 m | D16: =IF(A16>=$E$2,IF(A16<$E$2+$H$2,$P$2,0),IF(B16<Dashboard!$I$6,0,IF(A16>=$F$2,Dashboard!$C$23*POWER(1+$C$2,A16-$F$2),Dashboard!$C$23))) -> 0 | E16: =IF(A16>=$F$2,0,IF(A16=0,Dashboard!$G$10,IF(B16<Dashboard!$I$6,IF($J$2<=Dashboard!$H$10,Dashboard!$H$10,MAX(Dashboard!$H$10,MIN($J$2,Dashboard!$H$10*POWER($J$2/Dashboard!$H$10,A16/$D$2)))),$I$2-D16-Dashboard!$I$10-Dashboard!$J$10-Dashboard!$F$10*$I$2))) -> 592.04939 | F16: =IF(A16>=$F$2,$X$2*POWER(1+$C$2,A16-$F$2)+D16,0) -> 0 | G16: =IF(F16<=0,0,IF(F16*12<=18200,F16,IF(F16*12<=40712,(18200+(F16*12-18200)/0.84)/12,IF(F16*12<=103712,(45000+(F16*12-40712)/0.7)/12,IF(F16*12<=138362,(135000+(F16*12-103712)/0.63)/12,(190000+(F16*12-138362)/0.55)/12))))) -> 0 | H16: =IF(A16=$E$2,$W$2,0) -> 0 | I16: =E16-G16-H16 -> 592.04939 | J16: =IF(A16>=$F$2,$B$2,$A$2) -> 0.0079741404 | K16: =(K15+I16)*(1+J16) -> 116327.15 | L16: =IF(A16>=$F$2,K16,"") | M16: =IF(AND(A16<$E$2,E16>0),E16*POWER(1+$A$2,$E$2-A16),0) -> 1048.8516 | N16: =IF(M16<=0,0,IF($E$2-A16<12,(M16-E16)*Dashboard!$B$18,IF($Q$2+A16>=$R$2,MAX(0,M16-E16*POWER(1+$C$2,$E$2-A16))*MAX(Dashboard!$C$18,Dashboard!$B$18),IF($S$2<$R$2,(M16-E16)*0.5*Dashboard!$B$18,(E16*POWER(1+$A$2,$R$2-($Q$2+A16))-E16)*0.5*Dashboard!$B$18+MAX(0,M16-E16*POWER(1+$A$2,$R$2-($Q$2+A16))*POWER(1+$C$2,$S$2-$R$2))*MAX(Dashboard!$C$18,Dashboard!$B$18))))) -> 159.73762
A17: =A16+1 -> 12 | B17: =B16+1/12 -> 19.054795 | C17: =INT(B17)&" y "&ROUND((B17-INT(B17))*12,2)&" m" -> 19 y 0.66 m | D17: =IF(A17>=$E$2,IF(A17<$E$2+$H$2,$P$2,0),IF(B17<Dashboard!$I$6,0,IF(A17>=$F$2,Dashboard!$C$23*POWER(1+$C$2,A17-$F$2),Dashboard!$C$23))) -> 0 | E17: =IF(A17>=$F$2,0,IF(A17=0,Dashboard!$G$10,IF(B17<Dashboard!$I$6,IF($J$2<=Dashboard!$H$10,Dashboard!$H$10,MAX(Dashboard!$H$10,MIN($J$2,Dashboard!$H$10*POWER($J$2/Dashboard!$H$10,A17/$D$2)))),$I$2-D17-Dashboard!$I$10-Dashboard!$J$10-Dashboard!$F$10*$I$2))) -> 601.21467 | F17: =IF(A17>=$F$2,$X$2*POWER(1+$C$2,A17-$F$2)+D17,0) -> 0 | G17: =IF(F17<=0,0,IF(F17*12<=18200,F17,IF(F17*12<=40712,(18200+(F17*12-18200)/0.84)/12,IF(F17*12<=103712,(45000+(F17*12-40712)/0.7)/12,IF(F17*12<=138362,(135000+(F17*12-103712)/0.63)/12,(190000+(F17*12-138362)/0.55)/12))))) -> 0 | H17: =IF(A17=$E$2,$W$2,0) -> 0 | I17: =E17-G17-H17 -> 601.21467 | J17: =IF(A17>=$F$2,$B$2,$A$2) -> 0.0079741404 | K17: =(K16+I17)*(1+J17) -> 117860.77 | L17: =IF(A17>=$F$2,K17,"") | M17: =IF(AND(A17<$E$2,E17>0),E17*POWER(1+$A$2,$E$2-A17),0) -> 1056.6625 | N17: =IF(M17<=0,0,IF($E$2-A17<12,(M17-E17)*Dashboard!$B$18,IF($Q$2+A17>=$R$2,MAX(0,M17-E17*POWER(1+$C$2,$E$2-A17))*MAX(Dashboard!$C$18,Dashboard!$B$18),IF($S$2<$R$2,(M17-E17)*0.5*Dashboard!$B$18,(E17*POWER(1+$A$2,$R$2-($Q$2+A17))-E17)*0.5*Dashboard!$B$18+MAX(0,M17-E17*POWER(1+$A$2,$R$2-($Q$2+A17))*POWER(1+$C$2,$S$2-$R$2))*MAX(Dashboard!$C$18,Dashboard!$B$18))))) -> 159.80948
... A688: =A687+1 -> 683 | B688: =B687+1/12 -> 74.971461 | C688: =INT(B688)&" y "&ROUND((B688-INT(B688))*12,2)&" m" -> 74 y 11.66 m | D688: =IF(A688>=$E$2,IF(A688<$E$2+$H$2,$P$2,0),IF(B688<Dashboard!$I$6,0,IF(A688>=$F$2,Dashboard!$C$23*POWER(1+$C$2,A688-$F$2),Dashboard!$C$23))) -> 0 | E688: =IF(A688>=$F$2,0,IF(A688=0,Dashboard!$G$10,IF(B688<Dashboard!$I$6,IF($J$2<=Dashboard!$H$10,Dashboard!$H$10,MAX(Dashboard!$H$10,MIN($J$2,Dashboard!$H$10*POWER($J$2/Dashboard!$H$10,A688/$D$2)))),$I$2-D688-Dashboard!$I$10-Dashboard!$J$10-Dashboard!$F$10*$I$2))) -> 0 | F688: =IF(A688>=$F$2,$X$2*POWER(1+$C$2,A688-$F$2)+D688,0) -> 11717.297 | G688: =IF(F688<=0,0,IF(F688*12<=18200,F688,IF(F688*12<=40712,(18200+(F688*12-18200)/0.84)/12,IF(F688*12<=103712,(45000+(F688*12-40712)/0.7)/12,IF(F688*12<=138362,(135000+(F688*12-103712)/0.63)/12,(190000+(F688*12-138362)/0.55)/12))))) -> 16173.571 | H688: =IF(A688=$E$2,$W$2,0) -> 0 | I688: =E688-G688-H688 -> -16173.571 | J688: =IF(A688>=$F$2,$B$2,$A$2) -> 0.0079741404 | K688: =(K687+I688)*(1+J688) -> 37282535 | L688: =IF(A688>=$F$2,K688,"") -> 37282535 | M688: =IF(AND(A688<$E$2,E688>0),E688*POWER(1+$A$2,$E$2-A688),0) -> 0 | N688: =IF(M688<=0,0,IF($E$2-A688<12,(M688-E688)*Dashboard!$B$18,IF($Q$2+A688>=$R$2,MAX(0,M688-E688*POWER(1+$C$2,$E$2-A688))*MAX(Dashboard!$C$18,Dashboard!$B$18),IF($S$2<$R$2,(M688-E688)*0.5*Dashboard!$B$18,(E688*POWER(1+$A$2,$R$2-($Q$2+A688))-E688)*0.5*Dashboard!$B$18+MAX(0,M688-E688*POWER(1+$A$2,$R$2-($Q$2+A688))*POWER(1+$C$2,$S$2-$R$2))*MAX(Dashboard!$C$18,Dashboard!$B$18))))) -> 0
